{
    "questions":[
        {
            "index": 1,
            "image" : "https://www.aarb.org.br/wp-content/uploads/2019/07/iot-1080x608.jpg",
            "title": "Como acessar a dark web?",
            "answer": "2",
            "alternatives": [
                "não sei 1",
                "não sei 2",
                "não sei 3",
                "não sei 4",
                "não sei 5"
            ]
        },

        {
            "index": 2,
            "image" : "https://inforchannel.com.br/wp-content/uploads/2019/05/Iot.jpg",
            "title": "Como beber agua ?",
            "answer": "1",
            "alternatives": [
                "não sei 1",
                "não sei 2",
                "não sei 3",
                "não sei 4",
                "não sei 5"
            ]
        },
        {
            "index": 3,
            "waiting": true
        }
    ]
}